socialmediaborders/__init__.py
socialmediaborders/__main__.py
socialmediaborders/create_borders.py
socialmediaborders-0.0.3.dist-info/METADATA
socialmediaborders-0.0.3.dist-info/WHEEL
socialmediaborders-0.0.3.dist-info/entry_points.txt
socialmediaborders-0.0.3.dist-info/licenses/LICENCE.txt
socialmediaborders-0.0.3.dist-info/RECORD
