Metadata-Version: 2.1
Name: socialmediaborders
Version: 0.0.3
Summary: Adding colored borders to pictures for social media to bring them to a 1:1 format.
Project-URL: GitHub, https://github.com/agiagoulas/SocialMediaBorders
Author-email: Alexander Giagoulas <alexander@giagoulas.com>
License-Expression: MIT
License-File: LICENCE.txt
Classifier: License :: OSI Approved :: MIT License
Classifier: Operating System :: OS Independent
Classifier: Programming Language :: Python :: 3.9
Requires-Python: >=3.9
Requires-Dist: filetype
Requires-Dist: pillow
